Workbook
Name causa: #REF!
Name factor: #REF!
Name Tipo_de_Riesgo: [1]Listas!$C$3:$C$18
Name tipos: #REF!

Sheet Matriz de Riesgo
A1: Proceso: Infraestructura Tecnológica
A2: MATRIZ DE RIESGOS TECNOLOGICO
A3: Por: Agustín Sánchez
H4: Fecha de Elaboración: 24/11/2025
H5: Evaluación | O5: Tipo Control
A6: ID | B6: Código de Riesgo | C6: Subproceso | D6: Area | E6: Nombre del Riesgo | F6: Descripción de Riesgo | G6: Causa del Riesgo | H6: Pr | I6: S | J6: Valor Riesgo Bruto | K6: Riesgo Bruto | M6: Control | N6: Referencias del control | O6: M/A | P6: P/C | Q6: ValorEfec. Control
A7: 1 | B7: R01 | C7: Sistemas Operativos | D7: TI | E7: Ausencia de controles de contraseña robusto | F7: Los sistemas de registro de usuarios carecen de validación adecuada para asegurar que los usuarios establezcan contraseñas fuertes. | G7: La institución no cuenta con la validación adecuado para el proceso de registro, así como la falta de educación y conciencia de los usuarios; aunado a la falta de políticas organizacional en cuanto a seguridad de la información. | H7: 4 | I7: 4 | J7: =+H7*I7 -> 16 | K7: =IF(J7<2.9,"Bajo",IF(J7<5.9,"Moderado",IF(J7<9.9,"Medio","Alto"))) -> Alto | M7: Contratar al personal adecuado para realizar las actualizaciones necesarias a los software en cuando a seguridad. | N7: CIS Control 4: Uso controlado de privilegios administrativos; dicho control está asociado a la protección de las cuentas a partir de contraseñas seguras. | O7: A | P7: P | Q7: 1
A8: 2 | B8: R02 | C8: Comunicaciones oficiales | D8: TI | E8: Ausencia de MFA y filtrado avanzado en correo | F8: Las cuentas de correo se protegen solo con usuario y contraseña, sin doble factor ni políticas consistentes de filtrado anti-phishing, lo que facilita robo de credenciales. | G8: Dependencia histórica solo en contraseña, ausencia de política institucional que exija MFA y limitaciones en la configuración actual del servicio. | H8: 3 | I8: 4 | J8: =+H8*I8 -> 12 | K8: =IF(J8<2.9,"Bajo",IF(J8<5.9,"Moderado",IF(J8<9.9,"Medio","Alto"))) -> Alto | M8: Habilitar autenticación multifactor para usuarios críticos, endurecer las políticas de correo (SPF, DKIM, DMARC) y activar filtros de phishing y malware a nivel de servidor. | N8: CIS Control 6: Gestión de control de acceso: establece que el acceso a servicios críticos (como correo) debe reforzarse con autenticación fuerte y controles adicionales. | O8: A | P8: C | Q8: 1
A9: 3 | B9: R03 | C9: Plataforma de aulas virtuales | D9: TI | E9: Falta de monitoreo y plan de continuidad del aula virtual | F9: No existe un monitoreo proactivo del rendimiento ni un procedimiento formal para actuar ante caídas del sistema, afectando evaluaciones y clases en línea | G9: Crecimiento del uso de la plataforma sin que se haya actualizado formalmente la gestión de capacidad, monitoreo y continuidad del servicio. | H9: 3 | I9: 3 | J9: =+H9*I9 -> 9 | K9: =IF(J9<2.9,"Bajo",IF(J9<5.9,"Moderado",IF(J9<9.9,"Medio","Alto"))) -> Medio | M9: Implementar monitoreo 24/7 de disponibilidad, alarmas, procedimientos de respuesta y un plan de recuperación documentado para la plataforma virtual. | N9: CIS Control 17: Gestión de respuesta a incidentes: indica que se deben definir planes, roles y procedimientos ante incidentes que afecten servicios críticos como el aula virtual. | O9: A | P9: P | Q9: 1
A10: 4 | B10: R04 | C10: Monitoreo y auditoría | D10: TI | E10: Registros de seguridad dispersos y sin centralización | F10: Cada servidor genera logs de manera aislada; no existe un sistema centralizado que permita correlacionar eventos ni detectar patrones de ataque. | G10: Falta de inversión y proyecto específico para implementar solución de SIEM o plataforma de logs centralizada, pese al crecimiento de servicios. | H10: 3 | I10: 4 | J10: =+H10*I10 -> 12 | K10: =IF(J10<2.9,"Bajo",IF(J10<5.9,"Moderado",IF(J10<9.9,"Medio","Alto"))) -> Alto | M10: Implementar una solución de centralización de logs (SIEM o similar), definir qué eventos se recopilan y establecer alertas ante comportamientos anómalos. | N10: CIS Control 8: Gestión de registros de auditoría: exige recopilar, centralizar, proteger y revisar periódicamente los logs para apoyar la detección e investigación de incidentes. | O10: A | P10: P | Q10: 1
A11: 5 | B11: R05 | C11: Concienciación y formación | D11: TI | E11: Ausencia de programa formal y periódico de concienciación | F11: Las capacitaciones en ciberseguridad se realizan de forma esporádica y sin un programa anual; muchos usuarios desconocen buenas prácticas de uso de Wi-Fi, correo o contraseñas. | G11: No existe un plan institucional de formación en ciberseguridad con responsables, calendario y contenidos definidos. | H11: 4 | I11: 3 | J11: =+H11*I11 -> 12 | K11: =IF(J11<2.9,"Bajo",IF(J11<5.9,"Moderado",IF(J11<9.9,"Medio","Alto"))) -> Alto | M11: Diseñar e implementar un programa anual de concienciación (charlas, campañas, material digital) con métricas de participación y evaluación de aprendizaje. | N11: CIS Control 14: Formación y concienciación en seguridad: propone capacitar regularmente a los usuarios para reducir riesgos derivados del factor humano. | O11: M | P11: P | Q11: 1
A12: 6 | B12: R06 | C12: Evaluación de seguridad | D12: TI | E12: Ausencia de pruebas de penetración y evaluaciones técnicas periódicas | F12: No se realizan pruebas periódicas de pentesting o escaneos de seguridad completos que permitan identificar vulnerabilidades explotables en la infraestructura. | G12: Limitaciones de recursos y priorización de la operación diaria frente a actividades de prueba técnica formal y continua. | H12: 3 | I12: 4 | J12: =+H12*I12 -> 12 | K12: =IF(J12<2.9,"Bajo",IF(J12<5.9,"Moderado",IF(J12<9.9,"Medio","Alto"))) -> Alto | M12: Planificar y ejecutar, al menos una vez al año, pruebas de penetración y evaluaciones de vulnerabilidades con reporte formal y plan de remediación. | N12: CIS Control 18: Pruebas de penetración y ejercicios de red team: recomienda realizar pruebas controladas para validar la efectividad de los controles de seguridad implementados. | O12: M | P12: P | Q12: 1
A13: 7 | B13: R07 | C13: Servicios en línea | D13: TI | E13: Vulnerabilidades web por falta de pruebas de seguridad en las aplicaciones | F13: Los portales y aplicaciones web se actualizan funcionalmente, pero no pasan por pruebas de seguridad especializadas (OWASP), dejando posibles fallos de inyección, XSS o exposición de información. | G13: Ciclo de desarrollo enfocado en funcionalidades y tiempos de entrega, sin una etapa obligatoria de pruebas de seguridad en el SDLC. | H13: 3 | I13: 4 | J13: =+H13*I13 -> 12 | K13: =IF(J13<2.9,"Bajo",IF(J13<5.9,"Moderado",IF(J13<9.9,"Medio","Alto"))) -> Alto | M13: Incorporar análisis de código y escaneos de vulnerabilidades web, además de pruebas manuales basadas en OWASP, antes de publicar o actualizar aplicaciones. | N13: CIS Control 16: Seguridad en el ciclo de vida de desarrollo de software: establece que el desarrollo de software debe integrar revisiones y pruebas de seguridad para reducir vulnerabilidades explotables. | O13: A | P13: P | Q13: 1
A14: 8 | B14: R08 | C14: Gestión de software | D14: TI | E14: Uso de software no inventariado ni autorizado | F14: En los equipos se encuentran múltiples aplicaciones instaladas por los usuarios (descargas de Internet, versiones de prueba, herramientas no académicas) sin estar registradas ni aprobadas, lo que aumenta la superficie de ataque. | G14: No existe un inventario actualizado de software ni listas claras de aplicaciones permitidas/prohibidas para laboratorios y oficinas. | H14: 3 | I14: 3 | J14: =+H14*I14 -> 9 | K14: =IF(J14<2.9,"Bajo",IF(J14<5.9,"Moderado",IF(J14<9.9,"Medio","Alto"))) -> Medio | M14: Crear y mantener un inventario central de software, definir listas blancas y negras, y usar herramientas para impedir la instalación de aplicaciones no autorizadas en los equipos institucionales. | N14: CIS Control 2: Inventario y control de activos de software: establece que la organización debe identificar, registrar y controlar el software autorizado, bloqueando o eliminando aquel que no esté aprobado. | O14: A | P14: P | Q14: 1
A15: 9 | B15: R09 | C15: Administración de infraestructura de red | D15: TI | E15: Desconocimiento de todos los dispositivos de red instalados | F15: No hay un registro consolidado de todos los switches, routers, puntos de acceso y otros dispositivos de red por campus; algunos fueron instalados en proyectos antiguos y no figuran en el inventario actual. | G15: Falta de proceso formal para registrar en el inventario cada nuevo dispositivo de red y actualizarlo cuando se retiran o cambian equipos. | H15: 2 | I15: 4 | J15: =+H15*I15 -> 8 | K15: =IF(J15<2.9,"Bajo",IF(J15<5.9,"Moderado",IF(J15<9.9,"Medio","Alto"))) -> Medio | M15: Establecer un inventario de infraestructura de red que incluya modelo, serie, IP, ubicación física, responsable y estado, con revisiones periódicas para detectar dispositivos no autorizados. | N15: CIS Control 1: Inventario y control de activos empresariales: indica que la organización debe conocer todos los dispositivos conectados (incluidos equipos de red) para poder monitorearlos y protegerlos adecuadamente. | O15: M | P15: P | Q15: 1
A16: 10 | B16: R10 | C16: Servicios contratados | D16: TI | E16: Contratos con proveedores sin requisitos claros de seguridad | F16: Algunos contratos con plataformas externas (pagos, biblioteca, herramientas académicas) no incluyen cláusulas específicas sobre seguridad de la información, notificación de incidentes o ubicación/geografía de los datos. | G16: En los procesos de contratación se prioriza precio y funcionalidad, sin una plantilla estándar de requisitos de seguridad que se exija a todos los proveedores. | H16: 2 | I16: 4 | J16: =+H16*I16 -> 8 | K16: =IF(J16<2.9,"Bajo",IF(J16<5.9,"Moderado",IF(J16<9.9,"Medio","Alto"))) -> Medio | M16: Definir una política de gestión de proveedores que obligue a incluir en los contratos cláusulas mínimas de seguridad (controles, reportes, notificación de incidentes, cifrado, borrado de datos) y revisarlos antes de la firma. | N16: CIS Control 15: Gestión de proveedores de servicio: establece que se debe evaluar y gestionar a los proveedores, incluyendo requisitos de seguridad en los contratos y su revisión periódica para proteger plataformas y datos de la organización. | O16: M | P16: P | Q16: 1
A18: Pr = Probabilidad: 1-Bajo: una vez cada 2 o más años; 2-Moderado: una vez al año; 3-Alto: 4 veces al año; 4-Crítico: una vez al mes
A19: S = Severidad: 1-Bajo: Hasta $10,000; 2-Moderado: De $10,001 a $30,000; 3-Alto: De $30,001 $100,000; 4-Crítico: Más de $100,000.
A20: M/A: Control Manual o Automatizado
A21: P/C: Control Preventico o Correctivo

Sheet Plantilla Mitigación
B2: PROCESO DE FORTALECIMIENTO DE SISTEMAS OPERATIVOS
B3: PLAN DE MITIGACION PARA RIESGOS CALIFICADOS COMO RELEVANTES
B5: Proceso: #1
B6: Analista de Riesgo: Agustín Sánchez
B7: Dueño del Proceso: Muriel Jaramillo
B8: Fecha de aprobación: 24/11/2025
A10: # | B10: Descripción de Riesgo | C10: Factores de Riesgo | D10: Nivel del Riesgo Residual | E10: Plan de Acción | F10: Responsable | G10: Fecha estimada de Ejecución | H10: Fecha 1 Reprogramación | I10: Fecha 2 Reprogramación | J10: Fecha real de Implementación | K10: Observaciones | L10: Efec. Control
A11: ='Matriz de Riesgo'!A7 -> 1 | B11: ='Matriz de Riesgo'!F7 -> Los sistemas de registro de usuarios carecen de validación adecuada para asegurar que los usuarios establezcan contraseñas fuertes. | C11: Falta de políticas claras y configuración técnica de contraseñas (complejidad, bloqueo, caducidad), sumado al bajo nivel de concienciación de los usuarios. | D11: Moderado | E11: Evaluar y actualizar las políticas de contraseñas de la institución para garantizar que sean sólidas. Cocientizar al personal sobre la importancia de contraseñas fuertes y seguras. Cambiar periódicamente las contraseñas. | F11: ='Matriz de Riesgo'!D7 -> TI | G11: 45988 | L11: ='Matriz de Riesgo'!Q7 -> 1
A12: ='Matriz de Riesgo'!A8 -> 2 | B12: ='Matriz de Riesgo'!F8 -> Las cuentas de correo se protegen solo con usuario y contraseña, sin doble factor ni políticas consistentes de filtrado anti-phishing, lo que facilita robo de credenciales. | C12: Dependencia solo de contraseñas, ausencia de MFA y filtros anti-phishing robustos en el correo institucional, pese a su alta exposición a mensajes externos. | D12: Moderado | E12: Habilitar autenticación multifactor para las cuentas de correo institucional comenzando por usuarios críticos (TI, autoridades, finanzas). Configurar y reforzar los mecanismos SPF, DKIM y DMARC en el dominio institucional. Implementar filtros avanzados anti-phishing y antimalware en el servidor de correo y realizar campañas de simulación de phishing para medir y mejorar la respuesta de los usuarios. | F12: ='Matriz de Riesgo'!D8 -> TI | G12: 46025 | L12: ='Matriz de Riesgo'!Q8 -> 1
A13: ='Matriz de Riesgo'!A9 -> 3 | B13: ='Matriz de Riesgo'!F9 -> No existe un monitoreo proactivo del rendimiento ni un procedimiento formal para actuar ante caídas del sistema, afectando evaluaciones y clases en línea | C13: Crecimiento del uso del LMS sin monitoreo 24/7 ni plan formal de respuesta ante caídas, a pesar de ser crítico para clases y evaluaciones. | D13: Bajo | E13: Implementar herramientas de monitoreo 24/7 para la plataforma de aulas virtuales (disponibilidad, rendimiento y uso). Definir un procedimiento formal de respuesta ante caídas o degradación del servicio, incluyendo responsables y tiempos de recuperación esperados. Establecer respaldos frecuentes de la base de datos del LMS y pruebas periódicas de restauración para asegurar la continuidad académica. | F13: ='Matriz de Riesgo'!D9 -> TI | G13: 46029 | L13: ='Matriz de Riesgo'!Q9 -> 1
A14: ='Matriz de Riesgo'!A10 -> 4 | B14: ='Matriz de Riesgo'!F10 -> Cada servidor genera logs de manera aislada; no existe un sistema centralizado que permita correlacionar eventos ni detectar patrones de ataque. | C14: Cada servidor registra eventos de forma aislada, sin centralización ni revisión periódica, lo que impide detectar patrones de ataque. | D14: Medio | E14: Diseñar e implementar una solución de centralización de logs (SIEM o equivalente) que recoja eventos de los servidores, dispositivos de red y aplicaciones críticas. Definir qué eventos deben registrarse, el tiempo de retención y los responsables de su revisión periódica. Configurar alertas automáticas para eventos de seguridad relevantes y documentar los procedimientos de análisis e investigación. | F14: ='Matriz de Riesgo'!D10 -> TI | G14: 46033 | L14: ='Matriz de Riesgo'!Q10 -> 1
A15: ='Matriz de Riesgo'!A11 -> 5 | B15: ='Matriz de Riesgo'!F11 -> Las capacitaciones en ciberseguridad se realizan de forma esporádica y sin un programa anual; muchos usuarios desconocen buenas prácticas de uso de Wi-Fi, correo o contraseñas. | C15: No hay programa anual de formación en ciberseguridad; las charlas son puntuales y muchos usuarios desconocen las buenas prácticas básicas. | D15: Moderado | E15: Elaborar un programa anual de concienciación en ciberseguridad dirigido a docentes, administrativos y estudiantes. Planificar charlas, talleres y campañas digitales sobre temas clave (phishing, contraseñas, uso seguro de Wi-Fi, protección de datos). Establecer métricas de participación y evaluaciones breves para medir el nivel de comprensión y ajustar los contenidos en cada ciclo. | F15: ='Matriz de Riesgo'!D11 -> TI | G15: 46042 | L15: ='Matriz de Riesgo'!Q11 -> 1
A16: ='Matriz de Riesgo'!A12 -> 6 | B16: ='Matriz de Riesgo'!F12 -> No se realizan pruebas periódicas de pentesting o escaneos de seguridad completos que permitan identificar vulnerabilidades explotables en la infraestructura. | C16: No existe un calendario formal de pentesting ni escaneos de vulnerabilidades, por priorizar la operación diaria sobre la revisión de seguridad. | D16: Medio | E16: Definir un calendario anual de pruebas de penetración y escaneos de vulnerabilidades sobre la infraestructura crítica (servidores, aplicaciones web, red). Contratar servicios especializados o conformar un equipo interno que ejecute las pruebas siguiendo metodologías reconocidas. Documentar los hallazgos en informes formales, priorizar las vulnerabilidades y asignar responsables y fechas de cierre para la remediación. | F16: ='Matriz de Riesgo'!D12 -> TI | G16: 46055 | L16: ='Matriz de Riesgo'!Q12 -> 1
A17: ='Matriz de Riesgo'!A13 -> 7 | B17: ='Matriz de Riesgo'!F13 -> Los portales y aplicaciones web se actualizan funcionalmente, pero no pasan por pruebas de seguridad especializadas (OWASP), dejando posibles fallos de inyección, XSS o exposición de información. | C17: Las aplicaciones web se actualizan sin análisis automatizados ni pruebas OWASP, dejando posibles fallos de inyección y exposición de datos. | D17: Moderado | E17: Incorporar una fase obligatoria de pruebas de seguridad en el ciclo de desarrollo y actualización de aplicaciones web institucionales. Ejecutar análisis automatizados de vulnerabilidades (escáner web) y pruebas manuales basadas en OWASP antes de publicar cambios en producción. Mantener un registro de resultados, aplicar correcciones y volver a probar hasta cerrar las vulnerabilidades críticas y altas. | F17: ='Matriz de Riesgo'!D13 -> TI | G17: 46060 | L17: ='Matriz de Riesgo'!Q13 -> 1
A18: ='Matriz de Riesgo'!A14 -> 8 | B18: ='Matriz de Riesgo'!F14 -> En los equipos se encuentran múltiples aplicaciones instaladas por los usuarios (descargas de Internet, versiones de prueba, herramientas no académicas) sin estar registradas ni aprobadas, lo que aumenta la superficie de ataque. | C18: Los usuarios pueden instalar aplicaciones por su cuenta, sin inventario actualizado ni listas de software permitido/prohibido. | D18: Bajo | E18: Levantar un inventario completo del software instalado en laboratorios y oficinas administrativas. Definir una lista de aplicaciones autorizadas y no autorizadas según la función de cada área. Implementar herramientas de control de aplicaciones para bloquear instalaciones no permitidas y establecer un procedimiento para solicitar y aprobar nuevas herramientas de forma controlada. | F18: ='Matriz de Riesgo'!D14 -> TI | G18: 46069 | L18: ='Matriz de Riesgo'!Q14 -> 1
A19: ='Matriz de Riesgo'!A15 -> 9 | B19: ='Matriz de Riesgo'!F15 -> No hay un registro consolidado de todos los switches, routers, puntos de acceso y otros dispositivos de red por campus; algunos fueron instalados en proyectos antiguos y no figuran en el inventario actual. | C19: No hay registro central de todos los switches, routers y AP, ni proceso formal para actualizar el inventario cuando se añaden o retiran equipos. | D19: Bajo | E19: Realizar un levantamiento físico y lógico de todos los dispositivos de red por campus (switches, routers, AP, firewalls), registrando modelo, serie, IP, ubicación y responsable. Crear y mantener un inventario centralizado que se actualice cada vez que se agregue, reubique o retire un equipo de red. Establecer revisiones periódicas para detectar dispositivos no autorizados o mal documentados. | F19: ='Matriz de Riesgo'!D15 -> TI | G19: 46075 | L19: ='Matriz de Riesgo'!Q15 -> 1
A20: ='Matriz de Riesgo'!A16 -> 10 | B20: ='Matriz de Riesgo'!F16 -> Algunos contratos con plataformas externas (pagos, biblioteca, herramientas académicas) no incluyen cláusulas específicas sobre seguridad de la información, notificación de incidentes o ubicación/geografía de los datos. | C20: Se prioriza precio y funcionalidad en los contratos con proveedores, sin exigir requisitos mínimos de seguridad ni manejo adecuado de datos. | D20: Bajo | E20: Diseñar una plantilla estándar de requisitos de seguridad de la información para ser incluida en todos los contratos con proveedores de servicios tecnológicos. Revisar los contratos vigentes más críticos (pagos, biblioteca, plataformas académicas) e incorporar, en la medida de lo posible, cláusulas de seguridad, notificación de incidentes, ubicación de datos y borrado seguro al finalizar el servicio. Coordinar con Compras y Asesoría Legal para que ningún nuevo contrato se firme sin revisión previa de dichos requisitos. | F20: ='Matriz de Riesgo'!D16 -> TI | G20: 46078 | L20: ='Matriz de Riesgo'!Q16 -> 1

Sheet Mapa de Riesgos
B1: RESUMEN DEL RIESGO BRUTO | M1: RESUMEN DEL RIESGO RESIDUAL
B4: Probabilidad | C4: Muy Probable | H4: =COUNTIFS('Matriz de Riesgo'!K:K,"Alto") -> 6 | M4: Probabilidad | N4: Muy Probable | S4: =COUNTIFS('Plantilla Mitigación'!D:D,"Alto") -> 0
C5: Probable | G5: =COUNTIFS('Matriz de Riesgo'!K:K,"Medio") -> 4 | N5: Probable | R5: =COUNTIFS('Plantilla Mitigación'!D:D,"Medio") -> 2
C6: Ocasional | F6: =COUNTIFS('Matriz de Riesgo'!K:K,"Moderado") -> 0 | N6: Ocasional | Q6: =COUNTIFS('Plantilla Mitigación'!D:D,"Moderado") -> 4
C7: Poco Probable | E7: =COUNTIFS('Matriz de Riesgo'!K:K,"Bajo") -> 0 | N7: Poco Probable | P7: =COUNTIFS('Plantilla Mitigación'!D:D,"Bajo") -> 4
E9: Bajo | F9: Moderado | G9: Medio | H9: Alto | P9: Bajo | Q9: Moderado | R9: Medio | S9: Alto
E10: Hasta US$20,000 | F10: Hasta US$50,000 | G10: Hasta US$100,000 | H10: Mas US$100,000 | P10: Hasta US$20,000 | Q10: Hasta US$50,000 | R10: Hasta US$100,000 | S10: Mas US$100,000
E11: IMPACTO | P11: IMPACTO
C14: Planes de Acción | H14: Frecuencia de Ocurrencia | J14: Nivel de Riesgo | K14: Calificación | L14: Calificación | M14: Descripción
C15: Alto | D15: Se definen Plan de Acción | H15: Una vez al año | J15: 1 | L15: Poco Probable | M15: Indica que los riesgos identificados se han presentado o se pueden presentar de forma muyocasional una vezal año o a más de una año
C16: Medio | D16: Se definen Plan de Acción | H16: Una vez cada 6meses | J16: 2 | L16: Ocasional | M16: Indica que los riesgos identificados se han presentado o se pueden presentar de forma ocasional cada seismeses.
C17: Moderado | D17: No requieren de Plan de Acción | H17: Una vez cada 3meses | J17: 3 | L17: Probable | M17: Indica que los riesgos identificados se han presentado o se pueden presentar de manera común durante cada tres meses.
C18: Bajo | D18: No requieren de Plan de Acción | H18: Una vez almes | J18: 4 | L18: Muy Probable | M18: Indica que los eventos derivados de un riesgo operacional se han presentado o se pueden presentar con un comportamiento muy a menudo durante un mes o en menos de unmes.
C20: Calificación | D20: Riesgo Bruto | J20: Nivel de Impacto sobre Patrimonio | M20: Nivel de Riesgo | N20: Calificación | P20: Efectivida del Control | Q20: Nivel de Riesgo | R20: Calificación
C21: 1.0 a 2.9 | D21: Bajo | J21: Hasta $20,000.00 | L21: 1 | N21: Menor | P21: => 75% | Q21: Efectivo
C22: 3.0 a 5.9 | D22: Moderado | J22: De $20,001 hasta $50,000 | L22: 2 | N22: Moderado | P22: 50 a 74.9% | Q22: Medianamente efectivo
C23: 6.0 a 9.9 | D23: Medio | J23: De $50,001 hasta $100,000 | L23: 3 | N23: Mayor | P23: 25 a 49.9% | Q23: Poco efectivo
C24: 10.0 a 16.0 | D24: Alto | J24: Más de $100,000 | L24: 4 | N24: Crìtico | P24: < 25% | Q24: Infectivo o inexistente
